{
  "date": "2026-04-02",
  "dayOfWeek": "목요일",
  "seqID": 7296,
  "source": "https://miniweb.imbc.com/Music/View?seqID=7296&progCode=RAMFM300",
  "youtube": null,
  "songs": [
    {
      "order": 1,
      "title": "MAN ON THE MOON",
      "artist": "OST / REM"
    },
    {
      "order": 2,
      "title": "DANCING IN THE DARK",
      "artist": "OST / BRUCE SPRINGSTEEN"
    },
    {
      "order": 3,
      "title": "LOWDOWN",
      "artist": "BOZ SCAGGS"
    },
    {
      "order": 4,
      "title": "EVERYBODY NEEDS SOMEBODY TO LOVE",
      "artist": "THE BLUES BROTHERS"
    },
    {
      "order": 5,
      "title": "APRIL COME SHE WILL",
      "artist": "OST / SIMON AND GARFUNKEL"
    },
    {
      "order": 6,
      "title": "TAKING CARE OF BUSINESS",
      "artist": "BACHMAN-TURNER OVERDRIVE"
    },
    {
      "order": 7,
      "title": "DILEMMA",
      "artist": "NELLY feat. KELLY ROWLAND"
    },
    {
      "order": 8,
      "title": "I'M YOUR BABY TONIGHT",
      "artist": "WHITNEY HOUSTON"
    },
    {
      "order": 9,
      "title": "Water",
      "artist": "Tyla"
    },
    {
      "order": 10,
      "title": "SWIM",
      "artist": "BTS (방탄소년단)"
    },
    {
      "order": 11,
      "title": "Body to Body",
      "artist": "BTS (방탄소년단)"
    },
    {
      "order": 12,
      "title": "Defying Gravity",
      "artist": "OST / Ariana Grande feat. Cynthia Erivo"
    },
    {
      "order": 13,
      "title": "A CASE OF YOU",
      "artist": "JAMES BLAKE"
    },
    {
      "order": 14,
      "title": "IT RUNS THROUGH ME",
      "artist": "TOM MISCH feat. DE LA SOUL"
    },
    {
      "order": 15,
      "title": "Little Blue",
      "artist": "Jacob Collier feat. Brandi Carlile"
    },
    {
      "order": 16,
      "title": "THE RAILROAD *LIVE",
      "artist": "GRAND FUNK RAILROAD"
    }
  ],
  "createdAt": "2026-04-11T02:06:19Z",
  "matchRate": 0
}